e2c_client/__init__.py
e2c_client/__main__.py
e2c_client/cli/__init__.py
e2c_client/cli/control.py
e2c_client/cli/monitor.py
e2c_client/cli/tools.py
e2c_client/lib/__init__.py
e2c_client/lib/utils/__init__.py
e2c_client/lib/utils/e2c_errors.py
e2c_client/lib/utils/hosts.py
e2c_client/lib/utils/map_nodes.py
e2c_client-0.1.14.dist-info/LICENSE
e2c_client-0.1.14.dist-info/METADATA
e2c_client-0.1.14.dist-info/WHEEL
e2c_client-0.1.14.dist-info/entry_points.txt
e2c_client-0.1.14.dist-info/top_level.txt
e2c_client-0.1.14.dist-info/RECORD
