Metadata-Version: 2.1
Name: e2c-client
Version: 0.1.14
Summary: ALMA Ethernet-To-CAN socket server Python client package for LRU monitoring and control.
Home-page: https://bitbucket.alma.cl/projects/ENG/repos/e2c-client
Author: Jose L. Ortiz / ADE
Author-email: jose.ortiz@alma.cl
License: LGPL-2.1-only
Platform: UNKNOWN
Classifier: Programming Language :: Python :: 3
Classifier: License :: OSI Approved :: GNU Lesser General Public License v2 or later (LGPLv2+)
Classifier: Operating System :: OS Independent
License-File: LICENSE
Requires-Dist: rich (>=10.13.0)
Requires-Dist: typer (>=0.11.0)
Provides-Extra: test
Requires-Dist: pytest ; extra == 'test'
